openpyscad/__init__.py
openpyscad/base.py
openpyscad/boolean.py
openpyscad/custom2dshapes.py
openpyscad/custom3dshapes.py
openpyscad/modifiers.py
openpyscad/shapes_2d.py
openpyscad/shapes_3d.py
openpyscad/transformations.py
openpyscad-0.5.0.dist-info/LICENSE
openpyscad-0.5.0.dist-info/WHEEL
openpyscad-0.5.0.dist-info/METADATA
openpyscad-0.5.0.dist-info/RECORD
