Metadata-Version: 2.1
Name: openpyscad
Version: 0.5.0
Summary: Python library to generate OpenSCAD source code
Home-page: https://github.com/taxpon/openpyscad
License: MIT
Author: Takuro Wada
Author-email: taxpon@gmail.com
Requires-Python: >=3.5,<4.0
Classifier: Intended Audience :: Developers
Classifier: License :: OSI Approved :: MIT License
Classifier: Programming Language :: Python :: 3
Classifier: Programming Language :: Python :: 3.5
Classifier: Programming Language :: Python :: 3.6
Classifier: Programming Language :: Python :: 3.7
Classifier: Programming Language :: Python :: 3.8
Classifier: Programming Language :: Python :: 3.9
Classifier: Topic :: Software Development :: Code Generators
Classifier: Topic :: Software Development :: Libraries :: Python Modules
Requires-Dist: six (>=1.14.0,<2.0.0)
Project-URL: Repository, https://github.com/taxpon/openpyscad
